bvz_distributions
