Metadata-Version: 2.1
Name: bvz-distributions
Version: 1.1
Summary: Gaussian and Binomial distributions
Author: Bas van Zomeren
